Metadata-Version: 2.1
Name: simplelayout-meitounao110
Version: 0.0.1
Summary: A simplelayout package
Home-page: https://github.com/idrl-assignment/3-simplelayout-package-meitounao110
Author: meitounao110
Author-email: 431041317@qq.com
License: UNKNOWN
Platform: UNKNOWN
Requires-Dist: matplotlib
Requires-Dist: numpy
Requires-Dist: scipy
Requires-Dist: pytest
